app/__init__.py
app/aws.py
app/basic_auth.py
app/config.py
app/filters.py
app/glogging.py
app/log.py
app/ssl_279.py
app/utils.py
app/views.py
haldane-0.3.0.dist-info/DESCRIPTION.rst
haldane-0.3.0.dist-info/METADATA
haldane-0.3.0.dist-info/RECORD
haldane-0.3.0.dist-info/WHEEL
haldane-0.3.0.dist-info/metadata.json
haldane-0.3.0.dist-info/top_level.txt
haldane-0.3.0.dist-info/zip-safe
