Metadata-Version: 2.0
Name: haldane
Version: 0.3.0
Summary: A friendly http interface to the aws api
Home-page: https://github.com/seatgeek/haldane
Author: SeatGeek
Author-email: opensource@seatgeek.com
License: BSD
Keywords: aws api
Platform: UNKNOWN
Requires-Dist: appdirs (==1.4.3)
Requires-Dist: attrs (==18.1.0)
Requires-Dist: blinker (==1.4)
Requires-Dist: boto3 (==1.7.19)
Requires-Dist: botocore (==1.10.19)
Requires-Dist: bugsnag (==3.4.2)
Requires-Dist: click (==6.7)
Requires-Dist: contextlib2 (==0.5.5)
Requires-Dist: docutils (==0.14)
Requires-Dist: enum-compat (==0.0.2)
Requires-Dist: enum34 (==1.1.6)
Requires-Dist: eventlet (==0.23.0)
Requires-Dist: Flask (==1.0.2)
Requires-Dist: funcsigs (==1.0.2)
Requires-Dist: futures (==3.2.0)
Requires-Dist: gevent (==1.3.0)
Requires-Dist: greenlet (==0.4.13)
Requires-Dist: gunicorn (==19.8.1)
Requires-Dist: inflection (==0.3.1)
Requires-Dist: itsdangerous (==0.24)
Requires-Dist: Jinja2 (==2.10)
Requires-Dist: jmespath (==0.9.3)
Requires-Dist: MarkupSafe (==1.0)
Requires-Dist: more-itertools (==4.1.0)
Requires-Dist: newrelic (==3.2.0.91)
Requires-Dist: nose (==1.3.7)
Requires-Dist: packaging (==17.1)
Requires-Dist: pluggy (==0.6.0)
Requires-Dist: psutil (==5.4.5)
Requires-Dist: py (==1.5.3)
Requires-Dist: py-lru-cache (==0.1.4)
Requires-Dist: pyparsing (==2.2.0)
Requires-Dist: pytest (==3.5.1)
Requires-Dist: python-dateutil (==2.7.3)
Requires-Dist: raven (==6.8.0)
Requires-Dist: s3transfer (==0.1.13)
Requires-Dist: six (==1.11.0)
Requires-Dist: WebOb (==1.8.1)
Requires-Dist: Werkzeug (==0.14.1)
